cdk_image_pipeline/__init__.py
cdk_image_pipeline/py.typed
cdk_image_pipeline/_jsii/__init__.py
cdk_image_pipeline/_jsii/cdk-image-pipeline@0.5.132.jsii.tgz
cdk_image_pipeline-0.5.132.dist-info/LICENSE
cdk_image_pipeline-0.5.132.dist-info/METADATA
cdk_image_pipeline-0.5.132.dist-info/WHEEL
cdk_image_pipeline-0.5.132.dist-info/top_level.txt
cdk_image_pipeline-0.5.132.dist-info/RECORD
