Metadata-Version: 2.1
Name: cdk-image-pipeline
Version: 0.5.132
Summary: Quickly deploy a complete EC2 Image Builder Image Pipeline using CDK
Home-page: https://github.com/aws-samples/cdk-image-pipeline.git
Author: Cameron Magee<magcamer@amazon.com>
License: Apache-2.0
Project-URL: Source, https://github.com/aws-samples/cdk-image-pipeline.git
Classifier: Intended Audience :: Developers
Classifier: Operating System :: OS Independent
Classifier: Programming Language :: JavaScript
Classifier: Programming Language :: Python :: 3 :: Only
Classifier: Programming Language :: Python :: 3.9
Classifier: Programming Language :: Python :: 3.10
Classifier: Programming Language :: Python :: 3.11
Classifier: Typing :: Typed
Classifier: Development Status :: 5 - Production/Stable
Classifier: License :: OSI Approved
Requires-Python: ~=3.9
License-File: LICENSE
Requires-Dist: aws-cdk-lib <3.0.0,>=2.224.0
Requires-Dist: constructs <11.0.0,>=10.4.3
Requires-Dist: jsii <2.0.0,>=1.119.0
Requires-Dist: publication >=0.0.3
Requires-Dist: typeguard <4.3.0,>=2.13.3
